build/lib/build/lib/commonpy/__init__.py
build/lib/build/lib/commonpy/log_handler.py
build/lib/build/lib/commonpy/simpleexceptioncontext.py
build/lib/commonpy/__init__.py
build/lib/commonpy/log_handler.py
build/lib/commonpy/simpleexceptioncontext.py
build/lib/ekcommon/__init__.py
commonpy/__init__.py
commonpy/log_handler.py
commonpy/simpleexceptioncontext.py
ekcommon/__init__.py
ekcommon-1.0.2.dist-info/LICENSE
ekcommon-1.0.2.dist-info/METADATA
ekcommon-1.0.2.dist-info/WHEEL
ekcommon-1.0.2.dist-info/top_level.txt
ekcommon-1.0.2.dist-info/RECORD
