Metadata-Version: 2.2
Name: ekcommon
Version: 1.0.2
Summary: Common hacks in python.
Author-email: eyal karni <eyalk5@gmail.com>
Classifier: License :: OSI Approved :: MIT License
Classifier: Programming Language :: Python
Classifier: Programming Language :: Python :: 3
License-File: LICENSE
Requires-Dist: Pyro5
Requires-Dist: pytz
